[
    {
      "id": 1,
      "companyName": "360 degree",
      "planId": "SM891",
      "ssn": "1234-12-2001",
      "firstName": "Logan",
      "lastName": "William",
      "priorStatus": "Terminated",
      "updatedStatus": "Re-Hired",
      "date": "10/20/2021 9:00 AM"
    },
    {
      "id": 2,
      "companyName": "Distribution corn",
      "planId": "SM892",
      "ssn": "1234-12-2002",
      "firstName": "Tony",
      "lastName": "William",
      "priorStatus": "Deccased",
      "updatedStatus": "Active",
      "date": "10/20/2021 9:00 AM"
    },
    {
      "id": 3,
      "companyName": "Kamala crop",
      "planId": "SM893",
      "ssn": "1234-12-2003",
      "firstName": "Sam",
      "lastName": "William",
      "priorStatus": "Deccased",
      "updatedStatus": "Joined",
      "date": "10/20/2021 9:00 AM"
    },
    {
      "id": 4,
      "companyName": "Kamala new one",
      "planId": "SM894",
      "ssn": "1234-12-2003",
      "firstName": "Sam",
      "lastName": "Man",
      "priorStatus": "Military leave",
      "updatedStatus": "Leave",
      "date": "10/20/2021 9:00 AM"
    },
    {
      "id": 5,
      "companyName": "Tony stark",
      "planId": "SM894",
      "ssn": "1234-12-2003",
      "firstName": "Sam",
      "lastName": "Man",
      "priorStatus": "Deccased",
      "updatedStatus": "Joined",
      "date": "10/20/2021 9:00 AM"
    },
    {
      "id": 6,
      "companyName": "Royal times",
      "planId": "SM894",
      "ssn": "1234-12-2003",
      "firstName": "Sam",
      "lastName": "Man",
      "priorStatus": "Military leave",
      "updatedStatus": "Leave",
      "date": "10/20/2021 9:00 AM"
    },
    {
      "id": 1,
      "companyName": "360 degree",
      "planId": "SM891",
      "ssn": "1234-12-2001",
      "firstName": "Logan",
      "lastName": "William",
      "priorStatus": "Terminated",
      "updatedStatus": "Re-Hired",
      "date": "10/20/2021 9:00 AM"
    },
    {
      "id": 2,
      "companyName": "Distribution corn",
      "planId": "SM892",
      "ssn": "1234-12-2002",
      "firstName": "Tony",
      "lastName": "William",
      "priorStatus": "Deccased",
      "updatedStatus": "Active",
      "date": "10/20/2021 9:00 AM"
    },
    {
      "id": 3,
      "companyName": "Kamala crop",
      "planId": "SM893",
      "ssn": "1234-12-2003",
      "firstName": "Sam",
      "lastName": "William",
      "priorStatus": "Deccased",
      "updatedStatus": "Joined",
      "date": "10/20/2021 9:00 AM"
    },
    {
      "id": 4,
      "companyName": "Kamala new one",
      "planId": "SM894",
      "ssn": "1234-12-2003",
      "firstName": "Sam",
      "lastName": "Man",
      "priorStatus": "Military leave",
      "updatedStatus": "Leave",
      "date": "10/20/2021 9:00 AM"
    },
    {
      "id": 5,
      "companyName": "Tony stark",
      "planId": "SM894",
      "ssn": "1234-12-2003",
      "firstName": "Sam",
      "lastName": "Man",
      "priorStatus": "Deccased",
      "updatedStatus": "Joined",
      "date": "10/20/2021 9:00 AM"
    },
    {
      "id": 6,
      "companyName": "Royal times",
      "planId": "SM894",
      "ssn": "1234-12-2003",
      "firstName": "Sam",
      "lastName": "Man",
      "priorStatus": "Military leave",
      "updatedStatus": "Leave",
      "date": "10/20/2021 9:00 AM"
    }
  ]
  