[
    {
      "id": 123,
      "payDate": "12/01/2019",
      "payPeriodHours": "12.00",
      "comments": "view",
      "tooltip": "Added through File ACME 123 Plan 123 with loan details L123 _12122019"
    },
    {
      "id": 123,
      "payDate": "12/01/2019",
      "payPeriodHours": "12.00",
      "comments": "view",
      "tooltip": "Added through File ACME 123 Plan 123 with loan details L123 _12122019"
    },
    {
      "id": 123,
      "payDate": "12/01/2019",
      "payPeriodHours": "12.00",
      "comments": "view",
      "tooltip": "Added through File ACME 123 Plan 123 with loan details L123 _12122019"
    }
  ]
  